README.md
setup.cfg
setup.py
mpesa/__init__.py
mpesa/services.py
mpesa/urls.py
mpesa/views.py
mpesa/tests/__init__.py
mpesa/tests/test_service.py
python_mpesa.egg-info/PKG-INFO
python_mpesa.egg-info/SOURCES.txt
python_mpesa.egg-info/dependency_links.txt
python_mpesa.egg-info/requires.txt
python_mpesa.egg-info/top_level.txt
tests/__init__.py
tests/test_service.py