Metadata-Version: 1.1
Name: python-mpesa
Version: 0.1.10
Summary: M-Pesa API G2 Python adapter
Home-page: https://goodup.com
Author: Loek van Gent
Author-email: hallo@loekvan.gent
License: BSD
Platform: UNKNOWN
Classifier: Environment :: Web Environment
Classifier: Intended Audience :: Developers
Classifier: Operating System :: OS Independent
Classifier: Programming Language :: Python
Classifier: Topic :: Internet :: WWW/HTTP
Classifier: Topic :: Internet :: WWW/HTTP :: Dynamic Content
